{"gr":{"class":["igraph"],"type":"list","length":10,"str":"List of 10"},"edgs.degs":{"class":["function"],"type":"closure","length":1,"str":"function (var)"},"A1":{"class":["dgCMatrix"],"type":"S4","length":100,"str":"Formal class 'dgCMatrix' [package \"Matrix\"] with 6 slots","slots":["i","p","Dim","Dimnames","x","factors"]},"cl":{"class":["function"],"type":"closure","length":1,"str":"function (v)"},"ev":{"class":["eigen"],"type":"list","length":2,"str":"List of 2","names":["values","vectors"]},"edg.deg":{"class":["function"],"type":"closure","length":1,"str":"function (tg, ed)"},"dbtemp":{"class":["igraph"],"type":"list","length":10,"str":"List of 10"},"g1":{"class":["igraph"],"type":"list","length":10,"str":"List of 10"},"cir":{"class":["matrix"],"type":"double","length":72,"str":"num [1:36, 1:2] 0 1 0 0.623 0.782 ..."},"db":{"class":["igraph"],"type":"list","length":10,"str":"List of 10"},"g2":{"class":["igraph"],"type":"list","length":10,"str":"List of 10"},"db2":{"class":["igraph"],"type":"list","length":10,"str":"List of 10"},"g3":{"class":["igraph"],"type":"list","length":10,"str":"List of 10"},"mysc":{"class":["function"],"type":"closure","length":1,"str":"function (var1, var2)"},"ne":{"class":["numeric"],"type":"double","length":12,"str":"num [1:12] 1 7 8 14 15 21 22 28 29 35 ..."},"cong":{"class":["numeric"],"type":"double","length":35,"str":"num [1:35] 4 4 4 9 4 9 4 6 4 4 ..."},"g":{"class":["igraph"],"type":"list","length":10,"str":"List of 10"},"A":{"class":["dgCMatrix"],"type":"S4","length":64,"str":"Formal class 'dgCMatrix' [package \"Matrix\"] with 6 slots","slots":["i","p","Dim","Dimnames","x","factors"]},"tA1":{"class":["dgCMatrix"],"type":"S4","length":100,"str":"Formal class 'dgCMatrix' [package \"Matrix\"] with 6 slots","slots":["i","p","Dim","Dimnames","x","factors"]},"cy":{"class":["igraph"],"type":"list","length":10,"str":"List of 10"},"i":{"class":["integer"],"type":"integer","length":1,"str":"int 5"},"vcir":{"class":["matrix"],"type":"double","length":14,"str":"num [1:7, 1:2] 1 0 0.623 0.782 -0.223 ..."},"j":{"class":["integer"],"type":"integer","length":1,"str":"int 7"},"EDs":{"class":["integer"],"type":"integer","length":9,"str":"int [1:9] 9 9 9 9 6 8 9 9 9"},"k":{"class":["numeric"],"type":"double","length":1,"str":"num 7"},"n":{"class":["numeric"],"type":"double","length":1,"str":"num 5"},"tg1":{"class":["igraph"],"type":"list","length":10,"str":"List of 10"},"tgA1":{"class":["dgCMatrix"],"type":"S4","length":100,"str":"Formal class 'dgCMatrix' [package \"Matrix\"] with 6 slots","slots":["i","p","Dim","Dimnames","x","factors"]},"tdb":{"class":["igraph"],"type":"list","length":10,"str":"List of 10"},"tg2":{"class":["igraph"],"type":"list","length":10,"str":"List of 10"},"tdb2":{"class":["igraph"],"type":"list","length":10,"str":"List of 10"},"tg3":{"class":["igraph"],"type":"list","length":10,"str":"List of 10"},"vl":{"class":["list"],"type":"list","length":42,"str":"List of 42"},"edg.congestion":{"class":["function"],"type":"closure","length":1,"str":"function (g, tg, ed)"},"tree.congestion":{"class":["function"],"type":"closure","length":1,"str":"function (g, tg)"}}
